robo_slack_bot/eve_bot.py
robo_slack_bot/notes
robo_slack_bot/recipe_scraper.py
robo_slack_bot/slack_cleaner.py
robo_slack_bot-0.2.1.dev0.dist-info/entry_points.txt
robo_slack_bot-0.2.1.dev0.dist-info/LICENSE.txt
robo_slack_bot-0.2.1.dev0.dist-info/WHEEL
robo_slack_bot-0.2.1.dev0.dist-info/METADATA
robo_slack_bot-0.2.1.dev0.dist-info/RECORD
