Metadata-Version: 2.1
Name: robo-slack-bot
Version: 0.2.1.dev0
Summary: It is a slackbot
License: GPL-3
Author: John Stilia
Author-email: stilia.johny@gmail.com
Requires-Python: >=3.8,<4.0
Classifier: License :: Other/Proprietary License
Classifier: Programming Language :: Python :: 3
Classifier: Programming Language :: Python :: 3.10
Classifier: Programming Language :: Python :: 3.8
Classifier: Programming Language :: Python :: 3.9
Requires-Dist: Flask-Cors (>=3.0.10,<4.0.0)
Requires-Dist: elasticsearch (>=8.2.0,<9.0.0)
Requires-Dist: recipe-scrapers (>=13.32.1,<14.0.0)
Requires-Dist: slack (>=0.0.2,<0.0.3)
Requires-Dist: slack-cleaner2 (>=3.1.1,<4.0.0)
Requires-Dist: slackclient (>=2.9.4,<3.0.0)
Requires-Dist: slackeventsapi (>=3.0.1,<4.0.0)
Requires-Dist: validators (>=0.19.0,<0.20.0)
